gradio_overlay_video/__init__.py
gradio_overlay_video/keypoint_formats.py
gradio_overlay_video/overlay_video.py
gradio_overlay_video/overlay_video.pyi
gradio_overlay_video/visualization_processors.py
gradio_overlay_video/templates/component/index.js
gradio_overlay_video/templates/component/style.css
gradio_overlay_video/templates/component/assets/worker-BAOIWoxA.js
gradio_overlay_video/templates/example/index.js
gradio_overlay_video/templates/example/style.css
gradio_overlay_video/templates/example/assets/worker-BAOIWoxA.js
gradio_overlay_video-0.0.9.dist-info/METADATA
gradio_overlay_video-0.0.9.dist-info/WHEEL
gradio_overlay_video-0.0.9.dist-info/RECORD
