Metadata-Version: 2.4
Name: gradio_overlay_video
Version: 0.0.9
Summary: overlayed video controller
Author-email: Csaba Bolyós <bladeszasza@gmail.com>
License-Expression: Apache-2.0
Keywords: gradio-5,gradio-custom-component,laban-movement-analysis,movement-visualisation,pose visualisation,pose-estimation,video,visualisation
Classifier: Development Status :: 3 - Alpha
Classifier: Operating System :: OS Independent
Classifier: Programming Language :: Python :: 3
Classifier: Programming Language :: Python :: 3 :: Only
Classifier: Programming Language :: Python :: 3.8
Classifier: Programming Language :: Python :: 3.9
Classifier: Programming Language :: Python :: 3.10
Classifier: Programming Language :: Python :: 3.11
Classifier: Topic :: Scientific/Engineering
Classifier: Topic :: Scientific/Engineering :: Artificial Intelligence
Classifier: Topic :: Scientific/Engineering :: Visualization
Requires-Python: >=3.10
Requires-Dist: gradio<6.0,>=5.0
Provides-Extra: dev
Requires-Dist: build; extra == 'dev'
Requires-Dist: twine; extra == 'dev'
